HLTV/__init__.py
HLTV-0.2.0.dist-info/LICENSE.txt
HLTV-0.2.0.dist-info/METADATA
HLTV-0.2.0.dist-info/WHEEL
HLTV-0.2.0.dist-info/top_level.txt
HLTV-0.2.0.dist-info/RECORD
