Metadata-Version: 2.1
Name: HLTV
Version: 0.2.0
Summary: A python library that functions as a HLTV API to use in your code
Home-page: UNKNOWN
Author: Rushil Shah
License: UNKNOWN
Platform: UNKNOWN
Classifier: Programming Language :: Python :: 3
Classifier: License :: OSI Approved :: MIT License
Classifier: Operating System :: OS Independent
Requires-Python: >=3.6
